nonebot/adapters/onebot_qq_extension/__init__.py
nonebot/adapters/onebot_qq_extension/adapter.py
nonebot/adapters/onebot_qq_extension/bot.py
nonebot/adapters/onebot_qq_extension/bot.pyi
nonebot/adapters/onebot_qq_extension/event.py
nonebot/adapters/onebot_qq_extension/exception.py
nonebot/adapters/onebot_qq_extension/log.py
nonebot/adapters/onebot_qq_extension/message.py
nonebot/adapters/onebot_qq_extension/utils.py
onebot_qq_extension-0.1.2.dist-info/WHEEL
onebot_qq_extension-0.1.2.dist-info/METADATA
onebot_qq_extension-0.1.2.dist-info/RECORD
