Metadata-Version: 2.1
Name: onebot-qq-extension
Version: 0.1.2
Summary: 基于 OneBot v12 子协议 OneBot QQ Extension 实现的 nonebot2 适配器
Home-page: https://sclock.github.io/onebot-qq-extension/
License: MIT
Keywords: bot,qq,qqbot,coolq,onebot,cqhttp
Author: Sclock
Author-email: 1342810270@qq.com
Requires-Python: >=3.7.3,<4.0.0
Classifier: Development Status :: 5 - Production/Stable
Classifier: Framework :: Robot Framework
Classifier: Framework :: Robot Framework :: Library
Classifier: License :: OSI Approved :: MIT License
Classifier: Operating System :: OS Independent
Classifier: Programming Language :: Python :: 3
Classifier: Programming Language :: Python :: 3.10
Classifier: Programming Language :: Python :: 3.8
Classifier: Programming Language :: Python :: 3.9
Requires-Dist: nonebot-adapter-onebot (>=2.1.0,<3.0.0)
Requires-Dist: nonebot2 (>=2.0.0b3,<3.0.0)
Project-URL: Documentation, https://sclock.github.io/onebot-qq-extension/
Project-URL: Repository, https://github.com/Sclock/onebot-qq-extension
